{
    "ecg_phase_comp_atrial_func10": [
        "ECG_Phase_Completion_Atrial_max",
        "ECG_Phase_Completion_Atrial_min",
        "ECG_Phase_Completion_Atrial_mean",
        "ECG_Phase_Completion_Atrial_median",
        "ECG_Phase_Completion_Atrial_std",
        "ECG_Phase_Completion_Atrial_skewneww",
        "ECG_Phase_Completion_Atrial_kurtosis",
        "ECG_Phase_Completion_Atrial_low_quar",
        "ECG_Phase_Completion_Atrial_up_quar",
        "ECG_Phase_Completion_Atrial_quartile_range"
    ],
    "ecg_phase_comp_vent_func10": [
        "ECG_Phase_Completion_Ventricular_max",
        "ECG_Phase_Completion_Ventricular_min",
        "ECG_Phase_Completion_Ventricular_mean",
        "ECG_Phase_Completion_Ventricular_median",
        "ECG_Phase_Completion_Ventricular_std",
        "ECG_Phase_Completion_Ventricular_skewneww",
        "ECG_Phase_Completion_Ventricular_kurtosis",
        "ECG_Phase_Completion_Ventricular_low_quar",
        "ECG_Phase_Completion_Ventricular_up_quar",
        "ECG_Phase_Completion_Ventricular_quartile_range"
    ],
    "ecg_quality_func10": [
        "ECG_Quality_max",
        "ECG_Quality_min",
        "ECG_Quality_mean",
        "ECG_Quality_median",
        "ECG_Quality_std",
        "ECG_Quality_skewneww",
        "ECG_Quality_kurtosis",
        "ECG_Quality_low_quar",
        "ECG_Quality_up_quar",
        "ECG_Quality_quartile_range"
    ],
    "ecg_rate_func10": [
        "ECG_Rate_max",
        "ECG_Rate_min",
        "ECG_Rate_mean",
        "ECG_Rate_median",
        "ECG_Rate_std",
        "ECG_Rate_skewneww",
        "ECG_Rate_kurtosis",
        "ECG_Rate_low_quar",
        "ECG_Rate_up_quar",
        "ECG_Rate_quartile_range"
    ],
    "hrv_freq": [
        "HRV_ULF",
        "HRV_VLF",
        "HRV_LF",
        "HRV_HF",
        "HRV_VHF",
        "HRV_LFHF",
        "HRV_LFn",
        "HRV_HFn",
        "HRV_LnHF"
    ],
    "hrv_nonlin": [
        "HRV_SD1",
        "HRV_SD2",
        "HRV_SD1SD2",
        "HRV_S",
        "HRV_CSI",
        "HRV_CVI",
        "HRV_CSI_Modified",
        "HRV_PIP",
        "HRV_IALS",
        "HRV_PSS",
        "HRV_PAS",
        "HRV_GI",
        "HRV_SI",
        "HRV_AI",
        "HRV_PI",
        "HRV_C1d",
        "HRV_C1a",
        "HRV_SD1d",
        "HRV_SD1a",
        "HRV_C2d",
        "HRV_C2a",
        "HRV_SD2d",
        "HRV_SD2a",
        "HRV_Cd",
        "HRV_Ca",
        "HRV_SDNNd",
        "HRV_SDNNa",
        "HRV_ApEn",
        "HRV_SampEn"
    ],
    "hrv_time": [
        "HRV_RMSSD",
        "HRV_MeanNN",
        "HRV_SDNN",
        "HRV_SDSD",
        "HRV_CVNN",
        "HRV_CVSD",
        "HRV_MedianNN",
        "HRV_MadNN",
        "HRV_MCVNN",
        "HRV_IQRNN",
        "HRV_pNN50",
        "HRV_pNN20",
        "HRV_TINN",
        "HRV_HTI"
    ]
}